{"status": "OK", "has_more": true, "num_results": 20, "results": [{"byline": "BOSLEY CROWTHER", "headline": "Under the Paris Sky", "summary_short": "", "multimedia": null, "display_title": "Sous Le Ciel De Paris", "critics_pick": 0, "mpaa_rating": "", "date_updated": "2016-03-30 06:47:18", "opening_date": "1952-05-05", "link": {"url": "http://www.nytimes.com/movie/review?res=9D00E6DA133BE23BBC4E53DFB3668389649EDE", "type": "article", "suggested_link_text": "Read the New York Times Review of Sous Le Ciel De Paris"}, "publication_date": "1952-05-06"}, {"byline": "BOSLEY CROWTHER", "headline": "No Resting Place", "summary_short": "", "multimedia": null, "display_title": "No Resting Place", "critics_pick": 0, "mpaa_rating": "", "date_updated": "2016-03-30 07:16:24", "opening_date": null, "link": {"url": "http://www.nytimes.com/movie/review?res=9502E2DB133BE23BBC4D53DFB3668389649EDE", "type": "article", "suggested_link_text": "Read the New York Times Review of No Resting Place"}, "publication_date": "1952-05-05"}, {"byline": "H. H. T.", "headline": "Narrow Margin, The", "summary_short": "Lean, sizzling suspense on cross-country train. Not a Hitchcock but mighty close.", "multimedia": null, "display_title": "The Narrow Margin", "critics_pick": 0, "mpaa_rating": "Not Rated", "date_updated": "2016-03-30 07:25:30", "opening_date": "1952-05-04", "link": {"url": "http://www.nytimes.com/movie/review?res=9C07E3DB133BE23BBC4D53DFB3668389649EDE", "type": "article", "suggested_link_text": "Read the New York Times Review of The Narrow Margin"}, "publication_date": "1952-05-05"}, {"byline": "BOSLEY CROWTHER", "headline": "Pride of St Louis, The", "summary_short": "The Dizzy Dean baseball story. Surprisingly warm and funny.", "multimedia": null, "display_title": "The Pride of St. Louis", "critics_pick": 0, "mpaa_rating": "Not Rated", "date_updated": "2016-03-30 07:20:03", "opening_date": null, "link": {"url": "http://www.nytimes.com/movie/review?res=9406E4D9103CE53ABC4B53DFB3668389649EDE", "type": "article", "suggested_link_text": "Read the New York Times Review of The Pride of St. Louis"}, "publication_date": "1952-05-03"}, {"byline": "H. H. T.", "headline": "Belles on Their Toes", "summary_short": "Widow trying to support 12 children. Sentimental sequel to &quot;Cheaper by the Dozen.&quot;", "multimedia": null, "display_title": "Belles on Their Toes", "critics_pick": 0, "mpaa_rating": "", "date_updated": "2016-03-30 06:55:11", "opening_date": "1952-05-01", "link": {"url": "http://www.nytimes.com/movie/review?res=9506E4D9103CE53ABC4B53DFB3668389649EDE", "type": "article", "suggested_link_text": "Read the New York Times Review of Belles on Their Toes"}, "publication_date": "1952-05-03"}, {"byline": "H. H. T.", "headline": "Perfectionist, The", "summary_short": "", "multimedia": null, "display_title": "Un Grand Patron", "critics_pick": 0, "mpaa_rating": "", "date_updated": "2016-03-30 07:27:12", "opening_date": null, "link": {"url": "http://www.nytimes.com/movie/review?res=9D02E2DB173AE23BBC4A53DFB3668389649EDE", "type": "article", "suggested_link_text": "Read the New York Times Review of Un Grand Patron"}, "publication_date": "1952-05-02"}, {"byline": "BOSLEY CROWTHER", "headline": "Atomic City, The", "summary_short": "Fine, low-keyed suspense about kidnapped son of physicist. Lydia was, and is, Mrs. Charlton Heston.", "multimedia": null, "display_title": "The Atomic City", "critics_pick": 0, "mpaa_rating": "Not Rated", "date_updated": "2016-03-30 06:44:22", "opening_date": "1952-05-01", "link": {"url": "http://www.nytimes.com/movie/review?res=9503E2DB173AE23BBC4A53DFB3668389649EDE", "type": "article", "suggested_link_text": "Read the New York Times Review of The Atomic City"}, "publication_date": "1952-05-02"}, {"byline": "A. W.", "headline": "You Can't Beat the Irish", "summary_short": "", "multimedia": null, "display_title": "You Can't Beat the Irish", "critics_pick": 0, "mpaa_rating": "", "date_updated": "2016-03-30 06:46:54", "opening_date": "1952-04-30", "link": {"url": "http://www.nytimes.com/movie/review?res=9E05E5DB133BE23BBC4953DFB3668389649EDE", "type": "article", "suggested_link_text": "Read the New York Times Review of You Can't Beat the Irish"}, "publication_date": "1952-05-01"}, {"byline": "BOSLEY CROWTHER", "headline": "Macao", "summary_short": "Melodramatic junk but atmospheric direction by Josef von Sternberg.", "multimedia": null, "display_title": "Macao", "critics_pick": 0, "mpaa_rating": "", "date_updated": "2016-03-30 07:11:08", "opening_date": "1952-04-30", "link": {"url": "http://www.nytimes.com/movie/review?res=9D05E5DB133BE23BBC4953DFB3668389649EDE", "type": "article", "suggested_link_text": "Read the New York Times Review of Macao"}, "publication_date": "1952-05-01"}, {"byline": "BOSLEY CROWTHER", "headline": "Prize, The", "summary_short": "", "multimedia": null, "display_title": "The Prize", "critics_pick": 0, "mpaa_rating": "", "date_updated": "2016-03-30 06:42:24", "opening_date": null, "link": {"url": "http://www.nytimes.com/movie/review?res=9502E7DB173AE23BBC4850DFB2668389649EDE", "type": "article", "suggested_link_text": "Read the New York Times Review of The Prize"}, "publication_date": "1952-04-30"}, {"byline": "A. W.", "headline": "Edward and Caroline", "summary_short": "", "multimedia": null, "display_title": "Edouard et Caroline", "critics_pick": 0, "mpaa_rating": "", "date_updated": "2016-03-30 07:26:43", "opening_date": "1952-04-29", "link": {"url": "http://www.nytimes.com/movie/review?res=9900E0DC173AE23BBC4850DFB2668389649EDE", "type": "article", "suggested_link_text": "Read the New York Times Review of Edouard et Caroline"}, "publication_date": "1952-04-30"}, {"byline": "BOSLEY CROWTHER", "headline": "Never Take No for an Answer", "summary_short": "", "multimedia": null, "display_title": "Never Take No for an Answer", "critics_pick": 0, "mpaa_rating": "", "date_updated": "2016-03-30 06:41:45", "opening_date": null, "link": {"url": "http://www.nytimes.com/movie/review?res=9D02E4DC133BE23BBC4151DFB2668389649EDE", "type": "article", "suggested_link_text": "Read the New York Times Review of Never Take No for an Answer"}, "publication_date": "1952-04-29"}, {"byline": "BOSLEY CROWTHER", "headline": "Red Mountain", "summary_short": "Quantrill's Raiders. Good, thumping actioner.", "multimedia": null, "display_title": "Red Mountain", "critics_pick": 0, "mpaa_rating": "", "date_updated": "2016-03-30 07:12:47", "opening_date": "1951-11-01", "link": {"url": "http://www.nytimes.com/movie/review?res=9E04E3DC173AE23BBC4E51DFB2668389649EDE", "type": "article", "suggested_link_text": "Read the New York Times Review of Red Mountain"}, "publication_date": "1952-04-26"}, {"byline": "H. H. T.", "headline": "Loyola, The Soldier Saint", "summary_short": "", "multimedia": null, "display_title": "Loyola, the Soldier Saint", "critics_pick": 0, "mpaa_rating": "", "date_updated": "2016-03-30 06:43:03", "opening_date": null, "link": {"url": "http://www.nytimes.com/movie/review?res=9B0DEFDD173AE23BBC4D51DFB2668389649EDE", "type": "article", "suggested_link_text": "Read the New York Times Review of Loyola, the Soldier Saint"}, "publication_date": "1952-04-25"}, {"byline": "H. H. T.", "headline": "Okinawa", "summary_short": "World War II invasion. Burly and action packed.", "multimedia": null, "display_title": "Okinawa", "critics_pick": 0, "mpaa_rating": "", "date_updated": "2016-03-30 06:48:46", "opening_date": "1952-02-28", "link": {"url": "http://www.nytimes.com/movie/review?res=9F04EFDD133BE23BBC4C51DFB2668389649EDE", "type": "article", "suggested_link_text": "Read the New York Times Review of Okinawa"}, "publication_date": "1952-04-24"}, {"byline": "BOSLEY CROWTHER", "headline": "Mara Maru", "summary_short": "Lousy, lousy.", "multimedia": null, "display_title": "Mara Maru", "critics_pick": 0, "mpaa_rating": "", "date_updated": "2016-03-30 07:10:36", "opening_date": "1952-04-23", "link": {"url": "http://www.nytimes.com/movie/review?res=9C04EFDD133BE23BBC4C51DFB2668389649EDE", "type": "article", "suggested_link_text": "Read the New York Times Review of Mara Maru"}, "publication_date": "1952-04-24"}, {"byline": "A. W.", "headline": "Green Glove, The", "summary_short": "Minor postwar melodrama, good European canvas.", "multimedia": null, "display_title": "The Green Glove", "critics_pick": 0, "mpaa_rating": "", "date_updated": "2016-03-30 07:29:30", "opening_date": "1952-02-28", "link": {"url": "http://www.nytimes.com/movie/review?res=9D04EFDD133BE23BBC4C51DFB2668389649EDE", "type": "article", "suggested_link_text": "Read the New York Times Review of The Green Glove"}, "publication_date": "1952-04-24"}, {"byline": "BOSLEY CROWTHER", "headline": "Maytime in Mayfair", "summary_short": "", "multimedia": null, "display_title": "Maytime in Mayfair", "critics_pick": 0, "mpaa_rating": "", "date_updated": "2016-03-30 07:27:53", "opening_date": null, "link": {"url": "http://www.nytimes.com/movie/review?res=9D00EFDA103CE53ABC4B51DFB2668389649EDE", "type": "article", "suggested_link_text": "Read the New York Times Review of Maytime in Mayfair"}, "publication_date": "1952-04-23"}, {"byline": "BOSLEY CROWTHER", "headline": "Aaron Slick From Punkin Crick", "summary_short": "Slick, wide-eyed musical. On the plastic side.", "multimedia": null, "display_title": "Aaron Slick From Punkin Crick", "critics_pick": 0, "mpaa_rating": "", "date_updated": "2016-03-30 07:18:00", "opening_date": "1952-04-01", "link": {"url": "http://www.nytimes.com/movie/review?res=9906E1DE173AE23BBC4152DFB2668389649EDE", "type": "article", "suggested_link_text": "Read the New York Times Review of Aaron Slick From Punkin Crick"}, "publication_date": "1952-04-19"}, {"byline": "BOSLEY CROWTHER", "headline": "Valley of the Eagles", "summary_short": "", "multimedia": null, "display_title": "Valley of the Eagles", "critics_pick": 0, "mpaa_rating": "", "date_updated": "2016-03-30 06:57:15", "opening_date": "1952-04-25", "link": {"url": "http://www.nytimes.com/movie/review?res=9503E4D6163AE23BBC4952DFB2668389649EDE", "type": "article", "suggested_link_text": "Read the New York Times Review of Valley of the Eagles"}, "publication_date": "1952-04-11"}], "copyright": "Copyright (c) 2016 The New York Times Company. All Rights Reserved."}