{"status": "OK", "has_more": true, "num_results": 20, "results": [{"byline": "RICHARD W. NASON.", "headline": "Taiga", "summary_short": "", "multimedia": null, "display_title": "Taiga", "critics_pick": 0, "mpaa_rating": "", "date_updated": "2016-03-30 07:16:56", "opening_date": null, "link": {"url": "http://www.nytimes.com/movie/review?res=9903E7D6113FE53BBC4F52DFB5668382649EDE", "type": "article", "suggested_link_text": "Read the New York Times Review of Taiga"}, "publication_date": "1959-03-17"}, {"byline": "BOSLEY CROWTHER", "headline": "Sheriff of Fractured Jaw, The", "summary_short": "None too funny.", "multimedia": null, "display_title": "The Sheriff of Fractured Jaw", "critics_pick": 0, "mpaa_rating": "", "date_updated": "2016-03-30 07:21:18", "opening_date": null, "link": {"url": "http://www.nytimes.com/movie/review?res=9906E7DE1038EF3BBC4C52DFB5668382649EDE", "type": "article", "suggested_link_text": "Read the New York Times Review of The Sheriff of Fractured Jaw"}, "publication_date": "1959-03-14"}, {"byline": "HOWARD THOMPSON.", "headline": "House on Haunted Hill", "summary_short": "House of cards, the old spooky kind.", "multimedia": null, "display_title": "House on Haunted Hill", "critics_pick": 0, "mpaa_rating": "Not Rated", "date_updated": "2016-03-30 07:11:17", "opening_date": "1959-02-17", "link": {"url": "http://www.nytimes.com/movie/review?res=9A00E4D8113FE53BBC4A52DFB5668382649EDE", "type": "article", "suggested_link_text": "Read the New York Times Review of House on Haunted Hill"}, "publication_date": "1959-03-12"}, {"byline": "BOSLEY CROWTHER", "headline": "Law Is the Law, The", "summary_short": "", "multimedia": null, "display_title": "The Law Is the Law", "critics_pick": 0, "mpaa_rating": "", "date_updated": "2016-03-30 06:51:57", "opening_date": null, "link": {"url": "http://www.nytimes.com/movie/review?res=9F0DE7DA103EE63BBC4952DFB5668382649EDE", "type": "article", "suggested_link_text": "Read the New York Times Review of The Law Is the Law"}, "publication_date": "1959-03-11"}, {"byline": "A. H. WEILER.", "headline": "Up Periscope", "summary_short": "Submarine in WWII Pacific campaign. Dull, rah-rah Navy cliches.", "multimedia": null, "display_title": "Up Periscope", "critics_pick": 0, "mpaa_rating": "", "date_updated": "2016-03-30 07:16:38", "opening_date": null, "link": {"url": "http://www.nytimes.com/movie/review?res=9E02E0D7173DE73ABC4D53DFB5668382649EDE", "type": "article", "suggested_link_text": "Read the New York Times Review of Up Periscope"}, "publication_date": "1959-03-05"}, {"byline": "HOWARD THOMPSON", "headline": "Night of the Quarter Moon", "summary_short": "Tinny, lurid melodrama on miscegenation theme.", "multimedia": null, "display_title": "Night of the Quarter Moon", "critics_pick": 0, "mpaa_rating": "", "date_updated": "2016-03-30 06:52:32", "opening_date": null, "link": {"url": "http://www.nytimes.com/movie/review?res=9F02E0D7173DE73ABC4D53DFB5668382649EDE", "type": "article", "suggested_link_text": "Read the New York Times Review of Night of the Quarter Moon"}, "publication_date": "1959-03-05"}, {"byline": "BOSLEY CROWTHER", "headline": "Lonelyhearts", "summary_short": "West's newspaper columnist and troubled readers. Ugly, admirably aimed drama but doesn't make the grade.", "multimedia": null, "display_title": "Lonelyhearts", "critics_pick": 0, "mpaa_rating": "", "date_updated": "2016-03-30 06:45:56", "opening_date": "0000-00-00", "link": {"url": "http://www.nytimes.com/movie/review?res=9D02E0D7173DE73ABC4D53DFB5668382649EDE", "type": "article", "suggested_link_text": "Read the New York Times Review of Lonelyhearts"}, "publication_date": "1959-03-05"}, {"byline": "BOSLEY CROWTHER", "headline": "Stranger in my Arms", "summary_short": "Suds, with some helpful Astor brine.", "multimedia": null, "display_title": "Stranger in My Arms", "critics_pick": 0, "mpaa_rating": "", "date_updated": "2016-03-30 07:05:29", "opening_date": "1959-03-03", "link": {"url": "http://www.nytimes.com/movie/review?res=9800E3DD173EE43BBC4C53DFB5668382649EDE", "type": "article", "suggested_link_text": "Read the New York Times Review of Stranger in My Arms"}, "publication_date": "1959-03-04"}, {"byline": "BOSLEY CROWTHER", "headline": "Two-Headed Spy, The", "summary_short": "", "multimedia": null, "display_title": "The Two-Headed Spy", "critics_pick": 0, "mpaa_rating": "", "date_updated": "2016-03-30 06:55:58", "opening_date": null, "link": {"url": "http://www.nytimes.com/movie/review?res=9B04E2DF1F30E73BBC4B53DFB5668382649EDE", "type": "article", "suggested_link_text": "Read the New York Times Review of The Two-Headed Spy"}, "publication_date": "1959-03-03"}, {"byline": "RICHARD W. NASON.", "headline": "Liane, Jungle Goddess", "summary_short": "", "multimedia": null, "display_title": "Liane, Jungle Goddess", "critics_pick": 0, "mpaa_rating": "", "date_updated": "2016-03-30 07:15:16", "opening_date": null, "link": {"url": "http://www.nytimes.com/movie/review?res=9C07E4DA1338EF3BBC4B51DFB4668382649EDE", "type": "article", "suggested_link_text": "Read the New York Times Review of Liane, Jungle Goddess"}, "publication_date": "1959-02-23"}, {"byline": "HOWARD THOMPSON.", "headline": "Forbidden Fruit", "summary_short": "", "multimedia": null, "display_title": "Le Fruit defendu", "critics_pick": 0, "mpaa_rating": "", "date_updated": "2016-03-30 07:30:16", "opening_date": "1959-02-21", "link": {"url": "http://www.nytimes.com/movie/review?res=9404E4DA1338EF3BBC4B51DFB4668382649EDE", "type": "article", "suggested_link_text": "Read the New York Times Review of Le Fruit defendu"}, "publication_date": "1959-02-23"}, {"byline": "HOWARD THOMPSON.", "headline": "House on the Waterfront, The", "summary_short": "", "multimedia": null, "display_title": "The House on the Waterfront", "critics_pick": 0, "mpaa_rating": "", "date_updated": "2016-03-30 07:22:59", "opening_date": null, "link": {"url": "http://www.nytimes.com/movie/review?res=9E07E4DC113FE53BBC4951DFB4668382649EDE", "type": "article", "suggested_link_text": "Read the New York Times Review of The House on the Waterfront"}, "publication_date": "1959-02-21"}, {"byline": "BOSLEY CROWTHER", "headline": "Remarkable Mr Pennypacker, The", "summary_short": "Too much talk and Webb confidence.", "multimedia": null, "display_title": "The Remarkable Mr. Pennypacker", "critics_pick": 0, "mpaa_rating": "", "date_updated": "2016-03-30 06:43:35", "opening_date": null, "link": {"url": "http://www.nytimes.com/movie/review?res=9D07E4DC113FE53BBC4951DFB4668382649EDE", "type": "article", "suggested_link_text": "Read the New York Times Review of The Remarkable Mr. Pennypacker"}, "publication_date": "1959-02-21"}, {"byline": "BOSLEY CROWTHER", "headline": "Journey, The", "summary_short": "Refugee bus leaves revolution-torn Budapest, 1956. Longer on color than substance, but enough.", "multimedia": null, "display_title": "The Journey", "critics_pick": 0, "mpaa_rating": "", "date_updated": "2016-03-30 06:50:54", "opening_date": null, "link": {"url": "http://www.nytimes.com/movie/review?res=9E02E4DB113AE734A25753C2A9649C946892D6CF", "type": "article", "suggested_link_text": "Read the New York Times Review of The Journey"}, "publication_date": "1959-02-20"}, {"byline": "HOWARD THOMPSON.", "headline": "Last Mile, The", "summary_short": "The old death-row melodrama vivified by a sizzling Mick.", "multimedia": null, "display_title": "The Last Mile", "critics_pick": 0, "mpaa_rating": "", "date_updated": "2016-03-30 07:21:10", "opening_date": null, "link": {"url": "http://www.nytimes.com/movie/review?res=9B00EFDD103EE63BBC4152DFB4668382649EDE", "type": "article", "suggested_link_text": "Read the New York Times Review of The Last Mile"}, "publication_date": "1959-02-19"}, {"byline": "BOSLEY CROWTHER", "headline": "Sleeping Beauty", "summary_short": "", "multimedia": null, "display_title": "Sleeping Beauty", "critics_pick": 0, "mpaa_rating": "", "date_updated": "2016-03-30 07:15:01", "opening_date": null, "link": {"url": "http://www.nytimes.com/movie/review?res=9C0DE1DB1338EF3BBC4052DFB4668382649EDE", "type": "article", "suggested_link_text": "Read the New York Times Review of Sleeping Beauty"}, "publication_date": "1959-02-18"}, {"byline": "BOSLEY CROWTHER", "headline": "Black Orchid, The", "summary_short": "Woes of gangster's widow. Grey and moist.", "multimedia": null, "display_title": "The Black Orchid", "critics_pick": 0, "mpaa_rating": "", "date_updated": "2016-03-30 06:44:02", "opening_date": null, "link": {"url": "http://www.nytimes.com/movie/review?res=9E03E7D7103FE53BBC4B52DFB4668382649EDE", "type": "article", "suggested_link_text": "Read the New York Times Review of The Black Orchid"}, "publication_date": "1959-02-13"}, {"byline": "A. H. WEILER.", "headline": "Never Steal Anything Small", "summary_short": "Odd musical number, with Jim as waterfront union racketeer. Doesn't jive.", "multimedia": null, "display_title": "Never Steal Anything Small", "critics_pick": 0, "mpaa_rating": "", "date_updated": "2016-03-30 07:13:30", "opening_date": null, "link": {"url": "http://www.nytimes.com/movie/review?res=9503E5DB1E39E632A25751C1A9649C946892D6CF", "type": "article", "suggested_link_text": "Read the New York Times Review of Never Steal Anything Small"}, "publication_date": "1959-02-12"}, {"byline": "BOSLEY CROWTHER", "headline": "Hanging Tree, The", "summary_short": "Biting, offbeat western. Compelling story, highly effective Schell.", "multimedia": null, "display_title": "The Hanging Tree", "critics_pick": 0, "mpaa_rating": "", "date_updated": "2016-03-30 06:49:41", "opening_date": null, "link": {"url": "http://www.nytimes.com/movie/review?res=9C02E5DB1E39E632A25751C1A9649C946892D6CF", "type": "article", "suggested_link_text": "Read the New York Times Review of The Hanging Tree"}, "publication_date": "1959-02-12"}, {"byline": "HOWARD THOMPSON.", "headline": "Man Inside, The", "summary_short": "Fine scenery, feeble chase melodrama, good opener.", "multimedia": null, "display_title": "The Man Inside", "critics_pick": 0, "mpaa_rating": "", "date_updated": "2016-03-30 06:44:01", "opening_date": "1958-12-01", "link": {"url": "http://www.nytimes.com/movie/review?res=9B01E3DF123DE53BBC4D53DFB4668382649EDE", "type": "article", "suggested_link_text": "Read the New York Times Review of The Man Inside"}, "publication_date": "1959-02-05"}], "copyright": "Copyright (c) 2016 The New York Times Company. All Rights Reserved."}