{"status": "OK", "has_more": true, "num_results": 20, "results": [{"byline": "CARYN JAMES", "headline": "Pink Cadillac (Movie)", "summary_short": "Bounty hunter and kidnapped baby. Lazy, dull-witted action comedy.", "multimedia": null, "display_title": "Pink Cadillac", "critics_pick": 0, "mpaa_rating": "PG-13", "date_updated": "2016-03-30 06:54:50", "opening_date": "1989-05-26", "link": {"url": "http://www.nytimes.com/movie/review?res=9E0CEFDF153AF935A15756C0A96F948260", "type": "article", "suggested_link_text": "Read the New York Times Review of Pink Cadillac"}, "publication_date": "1989-05-26"}, {"byline": "Caryn James", "headline": "DIRECTED BY ANDREI TARKOVSKY (MOVIE)", "summary_short": "", "multimedia": null, "display_title": "Directed By Andrei Tarkovsky", "critics_pick": 0, "mpaa_rating": "", "date_updated": "2016-03-30 06:57:12", "opening_date": null, "link": {"url": "http://www.nytimes.com/movie/review?res=950DE1D91538F935A15756C0A96F948260", "type": "article", "suggested_link_text": "Read the New York Times Review of Directed By Andrei Tarkovsky"}, "publication_date": "1989-05-26"}, {"byline": "STEPHEN HOLDEN", "headline": "PATTES BLANCHES (MOVIE)", "summary_short": "", "multimedia": null, "display_title": "Pattes Blanches", "critics_pick": 0, "mpaa_rating": "", "date_updated": "2016-03-30 06:57:25", "opening_date": null, "link": {"url": "http://www.nytimes.com/movie/review?res=950DE4D91538F935A15756C0A96F948260", "type": "article", "suggested_link_text": "Read the New York Times Review of Pattes Blanches"}, "publication_date": "1989-05-26"}, {"byline": "Caryn James", "headline": "INDIANA JONES AND THE LAST CRUSADE (MOVIE)", "summary_short": "Pursuit of father and Holy Grail. Great fun.", "multimedia": null, "display_title": "Indiana Jones and the Last Crusade", "critics_pick": 0, "mpaa_rating": "", "date_updated": "2016-03-30 06:52:25", "opening_date": "1989-05-24", "link": {"url": "http://www.nytimes.com/movie/review?res=950DE4D81E3FF937A15756C0A96F948260", "type": "article", "suggested_link_text": "Read the New York Times Review of Indiana Jones and the Last Crusade"}, "publication_date": "1989-05-24"}, {"byline": "Vincent Canby", "headline": "MYSTERY TRAIN (MOVIE)", "summary_short": "Three Memphis-hotel tales, via Jarmusch. Original and buoyantly funny.", "multimedia": null, "display_title": "Mystery Train", "critics_pick": 0, "mpaa_rating": "R", "date_updated": "2016-03-30 06:45:52", "opening_date": "1989-11-17", "link": {"url": "http://www.nytimes.com/movie/review?res=9807E6DF153AF932A15756C0A96F948260", "type": "article", "suggested_link_text": "Read the New York Times Review of Mystery Train"}, "publication_date": "1989-05-21"}, {"byline": "Vincent Canby", "headline": "DO THE RIGHT THING (MOVIE)", "summary_short": "Racial confrontation in Bed-Stuy. Real and riveting, via Spike Lee.", "multimedia": null, "display_title": "Do the Right Thing", "critics_pick": 1, "mpaa_rating": "R", "date_updated": "2016-03-30 07:14:13", "opening_date": "1989-07-21", "link": {"url": "http://www.nytimes.com/movie/review?res=9905E5DF153AF933A15756C0A96F948260", "type": "article", "suggested_link_text": "Read the New York Times Review of Do the Right Thing"}, "publication_date": "1989-05-20"}, {"byline": "RICHARD BERNSTEIN", "headline": "HOW I GOT INTO COLLEGE (MOVIE)", "summary_short": "Unexceptional youth schemes to get into dream girl's school. As mediocre as its message.", "multimedia": null, "display_title": "How I Got Into College", "critics_pick": 0, "mpaa_rating": "PG-13", "date_updated": "2016-03-30 06:49:20", "opening_date": "1989-05-19", "link": {"url": "http://www.nytimes.com/movie/review?res=950DE1D61F3FF933A15756C0A96F948260", "type": "article", "suggested_link_text": "Read the New York Times Review of How I Got Into College"}, "publication_date": "1989-05-20"}, {"byline": "STEPHEN HOLDEN", "headline": "ESTHER (MOVIE)", "summary_short": "", "multimedia": null, "display_title": "Esther", "critics_pick": 0, "mpaa_rating": "", "date_updated": "2016-03-30 06:45:02", "opening_date": null, "link": {"url": "http://www.nytimes.com/movie/review?res=950DE1DE143AF93AA25756C0A96F948260", "type": "article", "suggested_link_text": "Read the New York Times Review of Esther"}, "publication_date": "1989-05-19"}, {"byline": "Caryn James", "headline": "ROAD HOUSE (MOVIE)", "summary_short": "Young barroom bouncer. Absurd.", "multimedia": null, "display_title": "Road House", "critics_pick": 0, "mpaa_rating": "R", "date_updated": "2016-03-30 06:57:52", "opening_date": "1989-05-19", "link": {"url": "http://www.nytimes.com/movie/review?res=950DE7D8163AF93AA25756C0A96F948260", "type": "article", "suggested_link_text": "Read the New York Times Review of Road House"}, "publication_date": "1989-05-19"}, {"byline": "Stephen Holden", "headline": "MIRACLE MILE (MOVIE)", "summary_short": "Jazz musician and waitress on eve of nuclear war.", "multimedia": null, "display_title": "Miracle Mile", "critics_pick": 0, "mpaa_rating": "R", "date_updated": "2016-03-30 07:09:58", "opening_date": "1989-05-19", "link": {"url": "http://www.nytimes.com/movie/review?res=950DE3DC143AF93AA25756C0A96F948260", "type": "article", "suggested_link_text": "Read the New York Times Review of Miracle Mile"}, "publication_date": "1989-05-19"}, {"byline": "Caryn James", "headline": "FOR QUEEN AND COUNTRY (MOVIE)", "summary_short": "Former British paratrooper returns to dismal London neighborhood. Strong, important and quietly polemical.", "multimedia": null, "display_title": "For Queen & Country", "critics_pick": 0, "mpaa_rating": "R", "date_updated": "2016-03-30 07:11:56", "opening_date": "1989-05-19", "link": {"url": "http://www.nytimes.com/movie/review?res=950DEEDE143AF93AA25756C0A96F948260", "type": "article", "suggested_link_text": "Read the New York Times Review of For Queen & Country"}, "publication_date": "1989-05-19"}, {"byline": "Caryn James", "headline": "COLD FEET (MOVIE)", "summary_short": "Loose-limbed, wry caper about anti-hero outlaws in a crackpot, contemporary West. Often hilarious.", "multimedia": null, "display_title": "Cold Feet", "critics_pick": 0, "mpaa_rating": "R", "date_updated": "2016-03-30 06:46:02", "opening_date": "1989-05-19", "link": {"url": "http://www.nytimes.com/movie/review?res=950DEFD61F3BF93AA25756C0A96F948260", "type": "article", "suggested_link_text": "Read the New York Times Review of Cold Feet"}, "publication_date": "1989-05-19"}, {"byline": "RICHARD BERNSTEIN", "headline": "BACK TO ARARAT (MOVIE)", "summary_short": "", "multimedia": null, "display_title": "Tillbaka Till Ararat", "critics_pick": 0, "mpaa_rating": "", "date_updated": "2016-03-30 07:27:58", "opening_date": null, "link": {"url": "http://www.nytimes.com/movie/review?res=950DE3DB143AF93AA25756C0A96F948260", "type": "article", "suggested_link_text": "Read the New York Times Review of Tillbaka Till Ararat"}, "publication_date": "1989-05-19"}, {"byline": "STEPHEN HOLDEN", "headline": "NIGHT IN HAVANA, A: DIZZY GILLESPIE IN CUBA (MOVIE)", "summary_short": "", "multimedia": null, "display_title": "A Night in Havana", "critics_pick": 0, "mpaa_rating": "", "date_updated": "2016-03-30 07:21:52", "opening_date": null, "link": {"url": "http://www.nytimes.com/movie/review?res=950DEEDA163AF93AA25756C0A96F948260", "type": "article", "suggested_link_text": "Read the New York Times Review of A Night in Havana"}, "publication_date": "1989-05-19"}, {"byline": "CARYN JAMES", "headline": "SUITORS, THE (MOVIE)", "summary_short": "", "multimedia": null, "display_title": "The Suitors", "critics_pick": 0, "mpaa_rating": "", "date_updated": "2016-03-30 07:27:33", "opening_date": null, "link": {"url": "http://www.nytimes.com/movie/review?res=950DE2D8113FF934A25756C0A96F948260", "type": "article", "suggested_link_text": "Read the New York Times Review of The Suitors"}, "publication_date": "1989-05-17"}, {"byline": "Caryn James", "headline": "VOICES FROM THE ATTIC (MOVIE)", "summary_short": "", "multimedia": null, "display_title": "Voices From the Attic", "critics_pick": 0, "mpaa_rating": "", "date_updated": "2016-03-30 06:45:28", "opening_date": null, "link": {"url": "http://www.nytimes.com/movie/review?res=950DEED7133AF931A25756C0A96F948260", "type": "article", "suggested_link_text": "Read the New York Times Review of Voices From the Attic"}, "publication_date": "1989-05-12"}, {"byline": "Vincent Canby", "headline": "SEE NO EVIL, HEAR NO EVIL (MOVIE)", "summary_short": "Disabled pair pool handicaps. Good, unlikely humor, though often not in the best of taste.", "multimedia": null, "display_title": "See No Evil, Hear No Evil", "critics_pick": 0, "mpaa_rating": "R", "date_updated": "2016-03-30 07:12:54", "opening_date": "1989-05-12", "link": {"url": "http://www.nytimes.com/movie/review?res=950DE1DC103AF931A25756C0A96F948260", "type": "article", "suggested_link_text": "Read the New York Times Review of See No Evil, Hear No Evil"}, "publication_date": "1989-05-12"}, {"byline": "Vincent Canby", "headline": "RETURN OF SWAMP THING, THE (MOVIE)", "summary_short": "Mad doctor turns into rubbery monster. More remake than sequel, and not as funny as it thinks.", "multimedia": null, "display_title": "The Return of Swamp Thing", "critics_pick": 0, "mpaa_rating": "PG-13", "date_updated": "2016-03-30 07:12:06", "opening_date": "1989-05-12", "link": {"url": "http://www.nytimes.com/movie/review?res=950DE0DD123AF931A25756C0A96F948260", "type": "article", "suggested_link_text": "Read the New York Times Review of The Return of Swamp Thing"}, "publication_date": "1989-05-12"}, {"byline": "Caryn James", "headline": "EARTH GIRLS ARE EASY (MOVIE)", "summary_short": "Flying saucer lands in pool. Good, perky sci-fi.", "multimedia": null, "display_title": "Earth Girls Are Easy", "critics_pick": 0, "mpaa_rating": "PG", "date_updated": "2016-03-30 06:45:09", "opening_date": "1989-05-12", "link": {"url": "http://www.nytimes.com/movie/review?res=950DEFD6163DF931A25756C0A96F948260", "type": "article", "suggested_link_text": "Read the New York Times Review of Earth Girls Are Easy"}, "publication_date": "1989-05-12"}, {"byline": "Stephen Holden", "headline": "FISTFIGHTER (MOVIE)", "summary_short": "Drifter avenges boxer pal's death, Arizona to South America. Strictly deadpan comic-book.", "multimedia": null, "display_title": "Fistfighter", "critics_pick": 0, "mpaa_rating": "R", "date_updated": "2016-03-30 07:13:07", "opening_date": "1989-05-12", "link": {"url": "http://www.nytimes.com/movie/review?res=950DE6D9123AF931A25756C0A96F948260", "type": "article", "suggested_link_text": "Read the New York Times Review of Fistfighter"}, "publication_date": "1989-05-12"}], "copyright": "Copyright (c) 2016 The New York Times Company. All Rights Reserved."}