{"status": "OK", "has_more": true, "num_results": 20, "results": [{"byline": "Janet Maslin", "headline": "Carbon Copy (Movie)", "summary_short": "White business exec learns he has black son. Interesting idea goes flimflam.", "multimedia": null, "display_title": "Carbon Copy", "critics_pick": 0, "mpaa_rating": "PG", "date_updated": "2016-03-30 07:29:06", "opening_date": "1981-09-25", "link": {"url": "http://www.nytimes.com/movie/review?res=9E0DE2D61138F936A1575AC0A967948260", "type": "article", "suggested_link_text": "Read the New York Times Review of Carbon Copy"}, "publication_date": "1981-09-25"}, {"byline": "Janet Maslin", "headline": "Disappearance, The (Movie)", "summary_short": "Hit-man obsessed with finding his missing wife. Highly overdrawn.", "multimedia": null, "display_title": "Disappearance", "critics_pick": 0, "mpaa_rating": "R", "date_updated": "2016-03-30 06:55:15", "opening_date": null, "link": {"url": "http://www.nytimes.com/movie/review?res=9C0CE2D61138F936A1575AC0A967948260", "type": "article", "suggested_link_text": "Read the New York Times Review of Disappearance"}, "publication_date": "1981-09-25"}, {"byline": "JANET MASLIN", "headline": "September Wheat (Movie)", "summary_short": "", "multimedia": null, "display_title": "Septemberweizen", "critics_pick": 0, "mpaa_rating": "", "date_updated": "2016-03-30 06:43:12", "opening_date": null, "link": {"url": "http://www.nytimes.com/movie/review?res=9B0DE7DC103BF937A1575AC0A967948260", "type": "article", "suggested_link_text": "Read the New York Times Review of Septemberweizen"}, "publication_date": "1981-09-24"}, {"byline": "VINCENT CANBY", "headline": "Only When I Laugh (Movie)", "summary_short": "Alcoholic actress tries again. Rounded, appealing Simon story, solidly played.", "multimedia": null, "display_title": "Only When I Laugh", "critics_pick": 0, "mpaa_rating": "R", "date_updated": "2016-03-30 06:49:06", "opening_date": "1981-09-25", "link": {"url": "http://www.nytimes.com/movie/review?res=9E07E7DF153BF930A1575AC0A967948260", "type": "article", "suggested_link_text": "Read the New York Times Review of Only When I Laugh"}, "publication_date": "1981-09-23"}, {"byline": "VINCENT CANBY", "headline": "El Salvador: Another Vietnam (Movie)", "summary_short": "", "multimedia": null, "display_title": "El Salvador: Another Vietnam", "critics_pick": 0, "mpaa_rating": "", "date_updated": "2016-03-30 07:14:36", "opening_date": null, "link": {"url": "http://www.nytimes.com/movie/review?res=9C06E2DA113BF93AA2575AC0A967948260", "type": "article", "suggested_link_text": "Read the New York Times Review of El Salvador: Another Vietnam"}, "publication_date": "1981-09-19"}, {"byline": "Vincent Canby", "headline": "THE FRENCH LIEUTENANT'S WOMAN (MOVIE)", "summary_short": "Fowles's lovely Victorian enigma. Compelling if flawed, and of course Meryl's marvelous.", "multimedia": null, "display_title": "The French Lieutenant's Woman", "critics_pick": 1, "mpaa_rating": "R", "date_updated": "2016-03-30 07:26:55", "opening_date": "1981-10-16", "link": {"url": "http://www.nytimes.com/movie/review?res=EE05E7DF1731E565BC4052DFBF66838A699EDE", "type": "article", "suggested_link_text": "Read the New York Times Review of The French Lieutenant's Woman"}, "publication_date": "1981-09-18"}, {"byline": "Vincent Canby", "headline": "Raggedy Man (Movie)", "summary_short": "Young Texas divorcee during WWII. Tender romance, affecting drama.", "multimedia": null, "display_title": "Raggedy Man", "critics_pick": 0, "mpaa_rating": "PG", "date_updated": "2016-03-30 07:26:20", "opening_date": "1981-09-18", "link": {"url": "http://www.nytimes.com/movie/review?res=9502E7DC103BF93BA2575AC0A967948260", "type": "article", "suggested_link_text": "Read the New York Times Review of Raggedy Man"}, "publication_date": "1981-09-18"}, {"byline": "JANET MASLIN", "headline": "Mommie Dearest (Movie)", "summary_short": "Joan Crawford's child-rearing practices, via daughter's book. Stinging stuff.", "multimedia": null, "display_title": "Mommie Dearest", "critics_pick": 0, "mpaa_rating": "R", "date_updated": "2016-03-30 07:11:05", "opening_date": "1981-09-25", "link": {"url": "http://www.nytimes.com/movie/review?res=9A05E7DF153BF93BA2575AC0A967948260", "type": "article", "suggested_link_text": "Read the New York Times Review of Mommie Dearest"}, "publication_date": "1981-09-18"}, {"byline": "Janet Maslin", "headline": "Continental Divide (Movie)", "summary_short": "Ornithologist and newspaperman in love. Brightly appealing comedy.", "multimedia": null, "display_title": "Continental Divide", "critics_pick": 0, "mpaa_rating": "PG", "date_updated": "2016-03-30 07:11:13", "opening_date": "1981-09-18", "link": {"url": "http://www.nytimes.com/movie/review?res=9506E1D61138F93BA2575AC0A967948260", "type": "article", "suggested_link_text": "Read the New York Times Review of Continental Divide"}, "publication_date": "1981-09-18"}, {"byline": "VINCENT CANBY", "headline": "Tim (Movie)", "summary_short": "Australian spinster and younger, mentally retarded gardener. Leisurely but moving. Impressive early Mel.", "multimedia": null, "display_title": "Tim", "critics_pick": 0, "mpaa_rating": "Not Rated", "date_updated": "2016-03-30 07:27:49", "opening_date": null, "link": {"url": "http://www.nytimes.com/movie/review?res=9E07E2DA113BF934A2575AC0A967948260", "type": "article", "suggested_link_text": "Read the New York Times Review of Tim"}, "publication_date": "1981-09-17"}, {"byline": "Vincent Canby", "headline": "SHOOTING PARTY, THE (MOVIE)", "summary_short": "Fascinating British class-structure drama, set in 1913 at nobleman's estate.", "multimedia": null, "display_title": "The Shooting Party", "critics_pick": 1, "mpaa_rating": "", "date_updated": "2016-03-30 07:05:33", "opening_date": "1985-09-01", "link": {"url": "http://www.nytimes.com/movie/review?res=9C03E7DC103BF932A2575AC0A967948260", "type": "article", "suggested_link_text": "Read the New York Times Review of The Shooting Party"}, "publication_date": "1981-09-11"}, {"byline": "JANET MASLIN", "headline": "14 Americans (Movie)", "summary_short": "", "multimedia": null, "display_title": "14 Americans: Directions of the 1970s", "critics_pick": 0, "mpaa_rating": "", "date_updated": "2016-03-30 06:55:26", "opening_date": null, "link": {"url": "http://www.nytimes.com/movie/review?res=9801E3D81038F93AA3575AC0A967948260", "type": "article", "suggested_link_text": "Read the New York Times Review of 14 Americans: Directions of the 1970s"}, "publication_date": "1981-09-09"}, {"byline": "JOHN CORRY", "headline": "Hell Night (Movie)", "summary_short": "Not really -- just a dull one.", "multimedia": null, "display_title": "Hell Night", "critics_pick": 0, "mpaa_rating": "R", "date_updated": "2016-03-30 06:54:12", "opening_date": "1981-08-28", "link": {"url": "http://www.nytimes.com/movie/review?res=9C0DEFDF153BF935A3575AC0A967948260", "type": "article", "suggested_link_text": "Read the New York Times Review of Hell Night"}, "publication_date": "1981-09-06"}, {"byline": "JANET MASLIN", "headline": "Night the Lights Went Out in Georgia, The (Movie)", "summary_short": "Singing siblings. Plain silly.", "multimedia": null, "display_title": "The Night the Lights Went Out in Georgia", "critics_pick": 0, "mpaa_rating": "PG", "date_updated": "2016-03-30 07:26:08", "opening_date": "1981-06-05", "link": {"url": "http://www.nytimes.com/movie/review?res=940CEFDF153BF936A3575AC0A967948260", "type": "article", "suggested_link_text": "Read the New York Times Review of The Night the Lights Went Out in Georgia"}, "publication_date": "1981-09-05"}, {"byline": "JOHN CORRY", "headline": "Condorman (Movie)", "summary_short": "Cartoonist pulled into international intrigue.", "multimedia": null, "display_title": "Condorman", "critics_pick": 0, "mpaa_rating": "PG", "date_updated": "2016-03-30 07:23:03", "opening_date": "1981-08-07", "link": {"url": "http://www.nytimes.com/movie/review?res=9905EEDA113BF932A0575BC0A967948260", "type": "article", "suggested_link_text": "Read the New York Times Review of Condorman"}, "publication_date": "1981-08-31"}, {"byline": "JOHN CORRY", "headline": "Private Lessons (Movie)", "summary_short": "European housekeeper seduces boss's teenage son and plots blackmail.", "multimedia": null, "display_title": "Private Lessons", "critics_pick": 0, "mpaa_rating": "R", "date_updated": "2016-03-30 06:47:04", "opening_date": "1981-08-28", "link": {"url": "http://www.nytimes.com/movie/review?res=9D0CE2DC103BF933A0575BC0A967948260", "type": "article", "suggested_link_text": "Read the New York Times Review of Private Lessons"}, "publication_date": "1981-08-30"}, {"byline": "Janet Maslin", "headline": "Chu Chu and the Philly Flash (Movie)", "summary_short": "Flat and painfully contrived, even with these two.", "multimedia": null, "display_title": "Chu Chu and the Philly Flash", "critics_pick": 0, "mpaa_rating": "PG", "date_updated": "2016-03-30 06:57:58", "opening_date": "1981-08-28", "link": {"url": "http://www.nytimes.com/movie/review?res=9B00E6DF1E38F93AA1575BC0A967948260", "type": "article", "suggested_link_text": "Read the New York Times Review of Chu Chu and the Philly Flash"}, "publication_date": "1981-08-29"}, {"byline": "Janet Maslin", "headline": "GALLIPOLI (MOVIE)", "summary_short": "Young Australian soldiers in WWI, via Weir. Stirring drama, with a shattering climax.", "multimedia": null, "display_title": "Gallipoli", "critics_pick": 1, "mpaa_rating": "PG", "date_updated": "2016-03-30 06:58:26", "opening_date": "1981-08-28", "link": {"url": "http://www.nytimes.com/movie/review?res=EE05E7DF1738B12CAB4A4CC8B6799D836896", "type": "article", "suggested_link_text": "Read the New York Times Review of Gallipoli"}, "publication_date": "1981-08-28"}, {"byline": "Janet Maslin", "headline": "BODY HEAT (MOVIE)", "summary_short": "Adultery and murder. Not in ``Double Indemnity'' league but good and steamy.", "multimedia": null, "display_title": "Body Heat", "critics_pick": 1, "mpaa_rating": "R", "date_updated": "2016-03-30 06:58:02", "opening_date": "1981-09-18", "link": {"url": "http://www.nytimes.com/movie/review?res=EE05E7DF173DE361BC4051DFBE66838A699EDE", "type": "article", "suggested_link_text": "Read the New York Times Review of Body Heat"}, "publication_date": "1981-08-28"}, {"byline": "Janet Maslin", "headline": "Honky Tonk Freeway (Movie)", "summary_short": "Scrambly Americana satire, more off than on, set in small Florida town. Some pearly bits.", "multimedia": null, "display_title": "Honky Tonk Freeway", "critics_pick": 0, "mpaa_rating": "PG", "date_updated": "2016-03-30 06:55:27", "opening_date": "1981-08-21", "link": {"url": "http://www.nytimes.com/movie/review?res=9506EFDF153BF932A1575BC0A967948260", "type": "article", "suggested_link_text": "Read the New York Times Review of Honky Tonk Freeway"}, "publication_date": "1981-08-21"}], "copyright": "Copyright (c) 2016 The New York Times Company. All Rights Reserved."}